zoneminder/__init__.py
zoneminder/exceptions.py
zoneminder/monitor.py
zoneminder/run_state.py
zoneminder/zm.py
zmha_py-0.5.3.post4.dist-info/LICENSE.md
zmha_py-0.5.3.post4.dist-info/METADATA
zmha_py-0.5.3.post4.dist-info/WHEEL
zmha_py-0.5.3.post4.dist-info/RECORD
