Metadata-Version: 2.1
Name: zmha-py
Version: 0.5.3.post4
Summary: 
Home-page: https://github.com/nabbi/zmha-py
License: Apache-2.0
Author: Nic Boet
Author-email: nic@boet.cc
Requires-Python: >=3.11,<4.0
Classifier: License :: OSI Approved :: Apache Software License
Classifier: Programming Language :: Python :: 3
Classifier: Programming Language :: Python :: 3.11
Classifier: Programming Language :: Python :: 3.12
Requires-Dist: requests (>=2.0)
Project-URL: Repository, https://github.com/nabbi/zmha-py
